LICENSE
MANIFEST.in
README.rst
setup.py
tests.py
wsgitestcase.py
wsgitestcase.egg-info/PKG-INFO
wsgitestcase.egg-info/SOURCES.txt
wsgitestcase.egg-info/dependency_links.txt
wsgitestcase.egg-info/requires.txt
wsgitestcase.egg-info/top_level.txt