Metadata-Version: 1.1
Name: wsgitestcase
Version: 0.1
Summary: TestCase that will launch your wsgi/werkzeug application in a separate thread for you
Home-page: https://github.com/bak1an/wsgitestcase
Author: Anton Baklanov
Author-email: antonbaklanov@gmail.com
License: MIT
Platform: UNKNOWN
Classifier: License :: OSI Approved :: MIT License
Classifier: Programming Language :: Python :: 2
Classifier: Programming Language :: Python :: 3
Classifier: Topic :: Software Development :: Testing
